[
    {
        "time": "19:00",
        "league": "UEFA Champions League",
        "home_team": {
            "name": "Arsenal",
            "logo": "https://media-sport.b-cdn.net/football/teams/42.png",
            "score": "0"
        },
        "away_team": {
            "name": "Paris Saint Germain",
            "logo": "https://media-sport.b-cdn.net/football/teams/85.png",
            "score": "1"
        },
        "video_link": [
            {
                "name": "Replay",
                "url": "https://vod.starxcdn.xyz/vod/paramount1-1745953200-10800.mp4/tracks-v1a1/mono.m3u8?auth_key=1746060221-ff1d71afcff244b7a5d8111af0087557-0-5bcf32a7309b469218c2633078e2b889"
            }
        ]
    },
    {
        "time": "18:45",
        "league": "Serie A",
        "home_team": {
            "name": "Lazio",
            "logo": "https://media-sport.b-cdn.net/football/teams/487.png",
            "score": "2"
        },
        "away_team": {
            "name": "Parma",
            "logo": "https://media-sport.b-cdn.net/football/teams/523.png",
            "score": "2"
        },
        "video_link": [
            {
                "name": "Replay",
                "url": "https://vod.starxcdn.xyz/vod/paramount2-1745865900-7800.mp4/tracks-v1a1/mono.m3u8?auth_key=1746060222-4c793bea93d54ac5aeed8c88555c42d2-0-00975d13eafa50f6e9e6e01cc032acf6"
            }
        ]
    },
    {
        "time": "18:45",
        "league": "Serie A",
        "home_team": {
            "name": "Verona",
            "logo": "https://media-sport.b-cdn.net/football/teams/504.png",
            "score": "0"
        },
        "away_team": {
            "name": "Cagliari",
            "logo": "https://media-sport.b-cdn.net/football/teams/490.png",
            "score": "2"
        },
        "video_link": [
            {
                "name": "Replay",
                "url": "https://vod.starxcdn.xyz/vod/paramount3-1745865900-7800.mp4/tracks-v1a1/mono.m3u8?auth_key=1746060223-e361377966804a26a75c4e4effa0b2bb-0-d24c04cd195223b07ec056f4fe0f323b"
            }
        ]
    },
    {
        "time": "18:45",
        "league": "Serie A",
        "home_team": {
            "name": "Napoli",
            "logo": "https://media-sport.b-cdn.net/football/teams/492.png",
            "score": "2"
        },
        "away_team": {
            "name": "Torino",
            "logo": "https://media-sport.b-cdn.net/football/teams/503.png",
            "score": "0"
        },
        "video_link": [
            {
                "name": "Replay",
                "url": "https://vod.starxcdn.xyz/vod/uk_bts1-1745779500-7800.mp4/tracks-v3a1/mono.m3u8?auth_key=1746060223-07f8b81f32bc4fd6ba593e8206e96393-0-d9b7a02c6569c8fdd92fe6ec59cf4f39"
            }
        ]
    },
    {
        "time": "18:45",
        "league": "Serie A",
        "home_team": {
            "name": "Atalanta",
            "logo": "https://media-sport.b-cdn.net/football/teams/499.png",
            "score": "1"
        },
        "away_team": {
            "name": "Lecce",
            "logo": "https://media-sport.b-cdn.net/football/teams/867.png",
            "score": "1"
        },
        "video_link": [
            {
                "name": "Replay",
                "url": "https://vod.starxcdn.xyz/vod/paramount7-1745779500-7800.mp4/tracks-v1a1/mono.m3u8?auth_key=1746060224-2cb5df237c5b41c4abf7d085bcbe2c62-0-77c6c84b49d17b994637ef499068b5e6"
            }
        ]
    },
    {
        "time": "16:00",
        "league": "Serie A",
        "home_team": {
            "name": "Juventus",
            "logo": "https://media-sport.b-cdn.net/football/teams/496.png",
            "score": "2"
        },
        "away_team": {
            "name": "Monza",
            "logo": "https://media-sport.b-cdn.net/football/teams/1579.png",
            "score": "0"
        },
        "video_link": [
            {
                "name": "Replay",
                "url": "https://vod.starxcdn.xyz/vod/paramount5-1745769600-7800.mp4/index.m3u8?auth_key=1746060225-c6def22cb29e4f57bfbba370973a6e8d-0-a8190d8e06f36acd2ce862f66f2fe006"
            }
        ]
    },
    {
        "time": "15:30",
        "league": "Premier League",
        "home_team": {
            "name": "Liverpool",
            "logo": "https://media-sport.b-cdn.net/football/teams/40.png",
            "score": "5"
        },
        "away_team": {
            "name": "Tottenham",
            "logo": "https://media-sport.b-cdn.net/football/teams/47.png",
            "score": "1"
        },
        "video_link": [
            {
                "name": "Replay",
                "url": "https://vod.starxcdn.xyz/vod/uk_ssepl-1745767800-7800.mp4/index.m3u8?auth_key=1746060226-e52d30d44f8c43c09467e73872ec188b-0-8b8a067b558e10ee5db5559cbf36e101"
            }
        ]
    },
    {
        "time": "15:30",
        "league": "Bundesliga",
        "home_team": {
            "name": "Werder Bremen",
            "logo": "https://media-sport.b-cdn.net/football/teams/162.png",
            "score": "0"
        },
        "away_team": {
            "name": "FC St. Pauli",
            "logo": "https://media-sport.b-cdn.net/football/teams/186.png",
            "score": "0"
        },
        "video_link": [
            {
                "name": "Replay",
                "url": "https://vod.starxcdn.xyz/vod/espn3-1745767800-7800.mp4/index.m3u8?auth_key=1746060227-6ee6768766854db8b28ed424d8d364e3-0-dd630a5312cda1f25de8e4944bd12672"
            }
        ]
    },
    {
        "time": "14:15",
        "league": "La Liga",
        "home_team": {
            "name": "Villarreal",
            "logo": "https://media-sport.b-cdn.net/football/teams/533.png",
            "score": "1"
        },
        "away_team": {
            "name": "Espanyol",
            "logo": "https://media-sport.b-cdn.net/football/teams/540.png",
            "score": "0"
        },
        "video_link": [
            {
                "name": "Replay",
                "url": "https://vod.starxcdn.xyz/vod/uk_premiersports2-1745763300-7800.mp4/index.m3u8?auth_key=1746060227-3f0679ccf033457f95718dc0ad659faa-0-a40dcf76bca8ee976bd40eed0f018c4d"
            }
        ]
    },
    {
        "time": "13:30",
        "league": "Bundesliga",
        "home_team": {
            "name": "VfL Bochum",
            "logo": "https://media-sport.b-cdn.net/football/teams/176.png",
            "score": "1"
        },
        "away_team": {
            "name": "Union Berlin",
            "logo": "https://media-sport.b-cdn.net/football/teams/182.png",
            "score": "1"
        },
        "video_link": [
            {
                "name": "Replay",
                "url": "https://vod.starxcdn.xyz/vod/espn0-1745760600-7800.mp4/index.m3u8?auth_key=1746060228-d3648d654c1046a8aef38f923aa77395-0-fd3c251219ee44de8a26e1874f839ba3"
            }
        ]
    },
    {
        "time": "13:00",
        "league": "Serie A",
        "home_team": {
            "name": "Fiorentina",
            "logo": "https://media-sport.b-cdn.net/football/teams/502.png",
            "score": "2"
        },
        "away_team": {
            "name": "Empoli",
            "logo": "https://media-sport.b-cdn.net/football/teams/511.png",
            "score": "1"
        },
        "video_link": [
            {
                "name": "Replay",
                "url": "https://vod.starxcdn.xyz/vod/paramount3-1745758800-7800.mp4/index.m3u8?auth_key=1746060229-b96d52100a0a4d769687fa112c340a07-0-b864d827b1a03a25019791272ae3f5bd"
            }
        ]
    },
    {
        "time": "13:00",
        "league": "Serie A",
        "home_team": {
            "name": "Inter",
            "logo": "https://media-sport.b-cdn.net/football/teams/505.png",
            "score": "0"
        },
        "away_team": {
            "name": "AS Roma",
            "logo": "https://media-sport.b-cdn.net/football/teams/497.png",
            "score": "1"
        },
        "video_link": [
            {
                "name": "Replay",
                "url": "https://vod.starxcdn.xyz/vod/uk_bts8-1745758800-7800.mp4/index.m3u8?auth_key=1746060230-11c2f1db66ed4d20a66a83ee241fe851-0-01ff496bb2d5cf5086b7a6f923e50947"
            }
        ]
    },
    {
        "time": "13:00",
        "league": "Premier League",
        "home_team": {
            "name": "Bournemouth",
            "logo": "https://media-sport.b-cdn.net/football/teams/35.png",
            "score": "1"
        },
        "away_team": {
            "name": "Manchester United",
            "logo": "https://media-sport.b-cdn.net/football/teams/33.png",
            "score": "1"
        },
        "video_link": [
            {
                "name": "Replay",
                "url": "https://vod.starxcdn.xyz/vod/uk_ssepl-1745758800-7800.mp4/index.m3u8?auth_key=1746060231-820ea771f5264fe9939bcf668649c96b-0-3e0b5ef0e3bc8e43c1d43e1a9d4201f8"
            }
        ]
    },
    {
        "time": "10:30",
        "league": "Serie A",
        "home_team": {
            "name": "Venezia",
            "logo": "https://media-sport.b-cdn.net/football/teams/517.png",
            "score": "0"
        },
        "away_team": {
            "name": "AC Milan",
            "logo": "https://media-sport.b-cdn.net/football/teams/489.png",
            "score": "2"
        },
        "video_link": [
            {
                "name": "Replay",
                "url": "https://vod.starxcdn.xyz/vod/paramount1-1745749800-7800.mp4/tracks-v1a1/mono.m3u8?auth_key=1746060232-4575ccb6d7c941ce955747accd6fd521-0-16aa137c1bf6fc56a636d7c0622e6b7f"
            }
        ]
    },
    {
        "time": "10:30",
        "league": "Serie A",
        "home_team": {
            "name": "Como",
            "logo": "https://media-sport.b-cdn.net/football/teams/895.png",
            "score": "1"
        },
        "away_team": {
            "name": "Genoa",
            "logo": "https://media-sport.b-cdn.net/football/teams/495.png",
            "score": "0"
        },
        "video_link": [
            {
                "name": "Replay",
                "url": "https://vod.starxcdn.xyz/vod/paramount2-1745749800-7800.mp4/tracks-v1a1/mono.m3u8?auth_key=1746060232-d11f9612b9d940fba145a54f151597f6-0-adbb04cd53f16d782fd045940db0cfca"
            }
        ]
    },
    {
        "time": "16:30",
        "league": "Bundesliga",
        "home_team": {
            "name": "Eintracht Frankfurt",
            "logo": "https://media-sport.b-cdn.net/football/teams/169.png",
            "score": "4"
        },
        "away_team": {
            "name": "RB Leipzig",
            "logo": "https://media-sport.b-cdn.net/football/teams/173.png",
            "score": "0"
        },
        "video_link": [
            {
                "name": "Replay",
                "url": "https://vod.starxcdn.xyz/vod/espn6-1745685000-7800.mp4/tracks-v1a1/mono.m3u8?auth_key=1746060233-23eeb4e137c8495bbcdcd0c18478f721-0-7d7d41402830d931a3e12e75a1e1a784"
            }
        ]
    },
    {
        "time": "16:15",
        "league": "FA Cup",
        "home_team": {
            "name": "Crystal Palace",
            "logo": "https://media-sport.b-cdn.net/football/teams/52.png",
            "score": "3"
        },
        "away_team": {
            "name": "Aston Villa",
            "logo": "https://media-sport.b-cdn.net/football/teams/66.png",
            "score": "0"
        },
        "video_link": [
            {
                "name": "Replay",
                "url": "https://vod.starxcdn.xyz/vod/uk_premiersports1-1745684100-10800.mp4/tracks-v3a1/mono.m3u8?auth_key=1746060234-cea7f8ad0e7347518a8246faf95ecd67-0-b6083264d162a90552e888080f332571"
            }
        ]
    },
    {
        "time": "14:00",
        "league": "Premier League",
        "home_team": {
            "name": "Brighton",
            "logo": "https://media-sport.b-cdn.net/football/teams/51.png",
            "score": "3"
        },
        "away_team": {
            "name": "West Ham",
            "logo": "https://media-sport.b-cdn.net/football/teams/48.png",
            "score": "2"
        },
        "video_link": [
            {
                "name": "Replay",
                "url": "https://vod.starxcdn.xyz/vod/epl_bra-1745676000-7800.mp4/index.m3u8?auth_key=1746060235-22113226a14641c1a748177af1c8af79-0-acb30f46c4cd24300c8df94588d54973"
            }
        ]
    },
    {
        "time": "14:00",
        "league": "Premier League",
        "home_team": {
            "name": "Southampton",
            "logo": "https://media-sport.b-cdn.net/football/teams/41.png",
            "score": "1"
        },
        "away_team": {
            "name": "Fulham",
            "logo": "https://media-sport.b-cdn.net/football/teams/36.png",
            "score": "2"
        },
        "video_link": [
            {
                "name": "Replay",
                "url": "https://vod.starxcdn.xyz/vod/epl_sou-1745676000-7800.mp4/index.m3u8?auth_key=1746060236-a1be4716bedb4288992282268c0d870e-0-b01752dcbe5e214b6c9f22419d45a446"
            }
        ]
    },
    {
        "time": "14:00",
        "league": "Premier League",
        "home_team": {
            "name": "Newcastle",
            "logo": "https://media-sport.b-cdn.net/football/teams/34.png",
            "score": "3"
        },
        "away_team": {
            "name": "Ipswich",
            "logo": "https://media-sport.b-cdn.net/football/teams/57.png",
            "score": "0"
        },
        "video_link": [
            {
                "name": "Replay",
                "url": "https://vod.starxcdn.xyz/vod/uk_premiersports1-1745676000-7800.mp4/index.m3u8?auth_key=1746060236-dd9eaad404a64d98b163f158a4a5d621-0-1435166e62b88097a630510bfc1513a1"
            }
        ]
    },
    {
        "time": "14:00",
        "league": "Premier League",
        "home_team": {
            "name": "Wolves",
            "logo": "https://media-sport.b-cdn.net/football/teams/39.png",
            "score": "3"
        },
        "away_team": {
            "name": "Leicester",
            "logo": "https://media-sport.b-cdn.net/football/teams/46.png",
            "score": "0"
        },
        "video_link": [
            {
                "name": "Replay",
                "url": "https://vod.starxcdn.xyz/vod/epl_wol-1745676000-7800.mp4/index.m3u8?auth_key=1746060237-ca24a8f42bef47f2b1a6d0b58fb05f6f-0-12ce368b88688b3b3bbcd5a6ae8da065"
            }
        ]
    },
    {
        "time": "13:30",
        "league": "Bundesliga",
        "home_team": {
            "name": "1899 Hoffenheim",
            "logo": "https://media-sport.b-cdn.net/football/teams/167.png",
            "score": "2"
        },
        "away_team": {
            "name": "Borussia Dortmund",
            "logo": "https://media-sport.b-cdn.net/football/teams/165.png",
            "score": "3"
        },
        "video_link": [
            {
                "name": "Replay",
                "url": "https://vod.starxcdn.xyz/vod/espn2-1745674200-7800.mp4/tracks-v1a1/mono.m3u8?auth_key=1746060238-27cc26b1668e4cbdb072835245d07969-0-37c544358d92a1cd223f5f196e23483c"
            }
        ]
    },
    {
        "time": "13:30",
        "league": "Bundesliga",
        "home_team": {
            "name": "VfL Wolfsburg",
            "logo": "https://media-sport.b-cdn.net/football/teams/161.png",
            "score": "0"
        },
        "away_team": {
            "name": "SC Freiburg",
            "logo": "https://media-sport.b-cdn.net/football/teams/160.png",
            "score": "1"
        },
        "video_link": [
            {
                "name": "Replay",
                "url": "https://vod.starxcdn.xyz/vod/espn1-1745674200-7800.mp4/tracks-v1a1/mono.m3u8?auth_key=1746060239-2265f2159958405781154388fc69cf65-0-22e1456d03281cfce88452cee5c2b86f"
            }
        ]
    },
    {
        "time": "13:30",
        "league": "Bundesliga",
        "home_team": {
            "name": "Bayern München",
            "logo": "https://media-sport.b-cdn.net/football/teams/157.png",
            "score": "3"
        },
        "away_team": {
            "name": "FSV Mainz 05",
            "logo": "https://media-sport.b-cdn.net/football/teams/164.png",
            "score": "0"
        },
        "video_link": [
            {
                "name": "Replay",
                "url": "https://vod.starxcdn.xyz/vod/espn0-1745674200-7800.mp4/tracks-v1a1/mono.m3u8?auth_key=1746060240-c3f3b43c1fd04a34b8c3a33fb44788c9-0-59945f0b351fe17d4e85aac5e2c62b05"
            }
        ]
    },
    {
        "time": "13:30",
        "league": "Bundesliga",
        "home_team": {
            "name": "Bayer Leverkusen",
            "logo": "https://media-sport.b-cdn.net/football/teams/168.png",
            "score": "2"
        },
        "away_team": {
            "name": "FC Augsburg",
            "logo": "https://media-sport.b-cdn.net/football/teams/170.png",
            "score": "0"
        },
        "video_link": [
            {
                "name": "Replay",
                "url": "https://vod.starxcdn.xyz/vod/espn3-1745674200-7800.mp4/tracks-v1a1/mono.m3u8?auth_key=1746060241-ff27296eadfa4a20b1ddec3b2777a2c6-0-8383131a21366afd44b008fda2e43ad2"
            }
        ]
    },
    {
        "time": "13:30",
        "league": "Bundesliga",
        "home_team": {
            "name": "Holstein Kiel",
            "logo": "https://media-sport.b-cdn.net/football/teams/191.png",
            "score": "4"
        },
        "away_team": {
            "name": "Borussia Mönchengladbach",
            "logo": "https://media-sport.b-cdn.net/football/teams/163.png",
            "score": "3"
        },
        "video_link": [
            {
                "name": "Replay",
                "url": "https://vod.starxcdn.xyz/vod/espn4-1745674200-7800.mp4/index.m3u8?auth_key=1746060241-54ae2047bb3d435ba2a8db6380163bc4-0-93368ae3ce932e2bfdf5a9d060dc46cc"
            }
        ]
    },
    {
        "time": "11:30",
        "league": "Premier League",
        "home_team": {
            "name": "Chelsea",
            "logo": "https://media-sport.b-cdn.net/football/teams/49.png",
            "score": "1"
        },
        "away_team": {
            "name": "Everton",
            "logo": "https://media-sport.b-cdn.net/football/teams/45.png",
            "score": "0"
        },
        "video_link": [
            {
                "name": "Replay",
                "url": "https://vod.starxcdn.xyz/vod/uk_bts1-1745667000-7800.mp4/tracks-v3a1/mono.m3u8?auth_key=1746060242-1231b5c4f3dc43b4827524596e0b8ead-0-7ccc2452e520435babb2a3d24c1820d5"
            }
        ]
    },
    {
        "time": "18:30",
        "league": "Bundesliga",
        "home_team": {
            "name": "VfB Stuttgart",
            "logo": "https://media-sport.b-cdn.net/football/teams/172.png",
            "score": "0"
        },
        "away_team": {
            "name": "1. FC Heidenheim",
            "logo": "https://media-sport.b-cdn.net/football/teams/180.png",
            "score": "1"
        },
        "video_link": [
            {
                "name": "Replay",
                "url": "https://vod.starxcdn.xyz/vod/espn0-1745605800-7800.mp4/tracks-v1a1/mono.m3u8?auth_key=1746060243-4207397924884ea2831a299b7b05f5ce-0-6b5e0d5d84a7a4593f9c2448e3e35fbc"
            }
        ]
    },
    {
        "time": "19:30",
        "league": "La Liga",
        "home_team": {
            "name": "Atletico Madrid",
            "logo": "https://media-sport.b-cdn.net/football/teams/530.png",
            "score": "3"
        },
        "away_team": {
            "name": "Rayo Vallecano",
            "logo": "https://media-sport.b-cdn.net/football/teams/728.png",
            "score": "0"
        },
        "video_link": [
            {
                "name": "Replay",
                "url": "https://vod.starxcdn.xyz/vod/uk_premiersports1-1745523000-7800.mp4/tracks-v3a1/mono.m3u8?auth_key=1746060244-877968d2926141c9aaf20febe7eba8a1-0-55ec40f5e82f8c8547cc93dc8ce71f52"
            }
        ]
    },
    {
        "time": "19:30",
        "league": "La Liga",
        "home_team": {
            "name": "Real Betis",
            "logo": "https://media-sport.b-cdn.net/football/teams/543.png",
            "score": "5"
        },
        "away_team": {
            "name": "Valladolid",
            "logo": "https://media-sport.b-cdn.net/football/teams/720.png",
            "score": "1"
        },
        "video_link": [
            {
                "name": "Replay",
                "url": "https://vod.starxcdn.xyz/vod/uk_premiersports2-1745523000-7800.mp4/tracks-v1a1/mono.m3u8?auth_key=1746060245-528183a3148f4997916b666ba27d9e8a-0-2101e2576c2354e00ff35eeff377f1fb"
            }
        ]
    },
    {
        "time": "17:00",
        "league": "La Liga",
        "home_team": {
            "name": "Leganes",
            "logo": "https://media-sport.b-cdn.net/football/teams/537.png",
            "score": "1"
        },
        "away_team": {
            "name": "Girona",
            "logo": "https://media-sport.b-cdn.net/football/teams/547.png",
            "score": "1"
        },
        "video_link": [
            {
                "name": "Replay",
                "url": "https://vod.starxcdn.xyz/vod/uk_premiersports2-1745514000-7800.mp4/tracks-v3a1/mono.m3u8?auth_key=1746060246-6179c06690354ab48bc6d0b33947204c-0-8a6785ad5077db8a881fe5c9651a8e62"
            }
        ]
    },
    {
        "time": "17:00",
        "league": "La Liga",
        "home_team": {
            "name": "Osasuna",
            "logo": "https://media-sport.b-cdn.net/football/teams/727.png",
            "score": "1"
        },
        "away_team": {
            "name": "Sevilla",
            "logo": "https://media-sport.b-cdn.net/football/teams/536.png",
            "score": "0"
        },
        "video_link": [
            {
                "name": "Replay",
                "url": "https://vod.starxcdn.xyz/vod/uk_premiersports1-1745514000-7800.mp4/tracks-v3a1/mono.m3u8?auth_key=1746060247-d6c6023312d843b7a1c7128f634151a5-0-4ddf8c513e6a162fe33f428c801cb5e3"
            }
        ]
    },
    {
        "time": "19:30",
        "league": "La Liga",
        "home_team": {
            "name": "Alaves",
            "logo": "https://media-sport.b-cdn.net/football/teams/542.png",
            "score": "1"
        },
        "away_team": {
            "name": "Real Sociedad",
            "logo": "https://media-sport.b-cdn.net/football/teams/548.png",
            "score": "0"
        },
        "video_link": [
            {
                "name": "Replay",
                "url": "https://vod.starxcdn.xyz/vod/espn2-1745436600-7800.mp4/tracks-v1a1/mono.m3u8?auth_key=1746060247-80d061c2aedd46ce98f10c6a9bd5bba8-0-c1673b87cd207b5e7ad9c167c18bf4fc"
            }
        ]
    },
    {
        "time": "19:30",
        "league": "La Liga",
        "home_team": {
            "name": "Getafe",
            "logo": "https://media-sport.b-cdn.net/football/teams/546.png",
            "score": "0"
        },
        "away_team": {
            "name": "Real Madrid",
            "logo": "https://media-sport.b-cdn.net/football/teams/541.png",
            "score": "1"
        },
        "video_link": [
            {
                "name": "Replay",
                "url": "https://vod.starxcdn.xyz/vod/uk_premiersports1-1745436600-7800.mp4/tracks-v3a1/mono.m3u8?auth_key=1746060248-1c5e3bf208874e0db1d0a93f9d58d3c4-0-0dc35787360316af086e4b59bfa56629"
            }
        ]
    },
    {
        "time": "19:00",
        "league": "Premier League",
        "home_team": {
            "name": "Arsenal",
            "logo": "https://media-sport.b-cdn.net/football/teams/42.png",
            "score": "2"
        },
        "away_team": {
            "name": "Crystal Palace",
            "logo": "https://media-sport.b-cdn.net/football/teams/52.png",
            "score": "2"
        },
        "video_link": [
            {
                "name": "Replay",
                "url": "https://vod.starxcdn.xyz/vod/uk_ssepl-1745434800-7800.mp4/tracks-v3a1/mono.m3u8?auth_key=1746060249-81b788b10d02443391ced1c01cbbed7f-0-f16396dc04da9bad2f2a7216f0f6a34d"
            }
        ]
    },
    {
        "time": "17:00",
        "league": "La Liga",
        "home_team": {
            "name": "Athletic Club",
            "logo": "https://media-sport.b-cdn.net/football/teams/531.png",
            "score": "1"
        },
        "away_team": {
            "name": "Las Palmas",
            "logo": "https://media-sport.b-cdn.net/football/teams/534.png",
            "score": "0"
        },
        "video_link": [
            {
                "name": "Replay",
                "url": "https://vod.starxcdn.xyz/vod/uk_premiersports1-1745427600-7800.mp4/tracks-v3a1/mono.m3u8?auth_key=1746060250-fcf01447b7ff4f1990b8f0813d6ef342-0-c2f19530bdb70a9d8d19deeb7b47f1e3"
            }
        ]
    },
    {
        "time": "17:00",
        "league": "La Liga",
        "home_team": {
            "name": "Celta Vigo",
            "logo": "https://media-sport.b-cdn.net/football/teams/538.png",
            "score": "3"
        },
        "away_team": {
            "name": "Villarreal",
            "logo": "https://media-sport.b-cdn.net/football/teams/533.png",
            "score": "0"
        },
        "video_link": [
            {
                "name": "Replay",
                "url": "https://vod.starxcdn.xyz/vod/uk_premiersports2-1745427600-7800.mp4/tracks-v3a1/mono.m3u8?auth_key=1746060251-7e42ab94ecd34ad6a4228ec3d6d22589-0-eb731d9fb1c2c1a06e362cdbe2e67ab6"
            }
        ]
    },
    {
        "time": "16:30",
        "league": "Serie A",
        "home_team": {
            "name": "Genoa",
            "logo": "https://media-sport.b-cdn.net/football/teams/495.png",
            "score": "0"
        },
        "away_team": {
            "name": "Lazio",
            "logo": "https://media-sport.b-cdn.net/football/teams/487.png",
            "score": "2"
        },
        "video_link": [
            {
                "name": "Replay",
                "url": "https://vod.starxcdn.xyz/vod/paramount3-1745425800-7800.mp4/tracks-v1a1/mono.m3u8?auth_key=1746060251-7c777844bdec40fe9c2424e3f94a5eab-0-61efdc7e1e62872cd30786e169d66d9d"
            }
        ]
    },
    {
        "time": "16:30",
        "league": "Serie A",
        "home_team": {
            "name": "Torino",
            "logo": "https://media-sport.b-cdn.net/football/teams/503.png",
            "score": "2"
        },
        "away_team": {
            "name": "Udinese",
            "logo": "https://media-sport.b-cdn.net/football/teams/494.png",
            "score": "0"
        },
        "video_link": [
            {
                "name": "Replay",
                "url": "https://vod.starxcdn.xyz/vod/paramount4-1745425800-7800.mp4/tracks-v1a1/mono.m3u8?auth_key=1746060252-35034ae62cff449ba54bb1f83f884cdd-0-de73f1029e75a995e1a2fa9692ca8d66"
            }
        ]
    },
    {
        "time": "16:30",
        "league": "Serie A",
        "home_team": {
            "name": "Parma",
            "logo": "https://media-sport.b-cdn.net/football/teams/523.png",
            "score": "1"
        },
        "away_team": {
            "name": "Juventus",
            "logo": "https://media-sport.b-cdn.net/football/teams/496.png",
            "score": "0"
        },
        "video_link": [
            {
                "name": "Replay",
                "url": "https://vod.starxcdn.xyz/vod/uk_bts2-1745425800-7800.mp4/tracks-v3a1/mono.m3u8?auth_key=1746060253-dc7a8c4eb2604ef6990361bf0035dfae-0-911a3c711470390351d21574ab6002cf"
            }
        ]
    },
    {
        "time": "16:30",
        "league": "Serie A",
        "home_team": {
            "name": "Cagliari",
            "logo": "https://media-sport.b-cdn.net/football/teams/490.png",
            "score": "1"
        },
        "away_team": {
            "name": "Fiorentina",
            "logo": "https://media-sport.b-cdn.net/football/teams/502.png",
            "score": "2"
        },
        "video_link": [
            {
                "name": "Replay",
                "url": "https://vod.starxcdn.xyz/vod/paramount2-1745425800-7800.mp4/tracks-v1a1/mono.m3u8?auth_key=1746060254-a4ac2df199f14aea84cf02beb5a27e81-0-89fac6eba7262e05f0196c8bdca296a7"
            }
        ]
    },
    {
        "time": "19:30",
        "league": "La Liga",
        "home_team": {
            "name": "Barcelona",
            "logo": "https://media-sport.b-cdn.net/football/teams/529.png",
            "score": "1"
        },
        "away_team": {
            "name": "Mallorca",
            "logo": "https://media-sport.b-cdn.net/football/teams/798.png",
            "score": "0"
        },
        "video_link": [
            {
                "name": "Replay",
                "url": "https://vod.starxcdn.xyz/vod/uk_premiersports1-1745350200-7800.mp4/tracks-v3a1/mono.m3u8?auth_key=1746060255-924cec554eb442f48ce4e70864738c97-0-078013d14ea64e11996ecacd0f9635a6"
            }
        ]
    },
    {
        "time": "19:00",
        "league": "Premier League",
        "home_team": {
            "name": "Manchester City",
            "logo": "https://media-sport.b-cdn.net/football/teams/50.png",
            "score": "2"
        },
        "away_team": {
            "name": "Aston Villa",
            "logo": "https://media-sport.b-cdn.net/football/teams/66.png",
            "score": "1"
        },
        "video_link": [
            {
                "name": "Replay",
                "url": "https://vod.starxcdn.xyz/vod/uk_ssepl-1745348400-7800.mp4/tracks-v3a1/mono.m3u8?auth_key=1746060256-991469ea6bc6444f902f59e5e15c8620-0-8f8ea0bf74d3be876fced69a3261e896"
            }
        ]
    },
    {
        "time": "17:00",
        "league": "La Liga",
        "home_team": {
            "name": "Valencia",
            "logo": "https://media-sport.b-cdn.net/football/teams/532.png",
            "score": "1"
        },
        "away_team": {
            "name": "Espanyol",
            "logo": "https://media-sport.b-cdn.net/football/teams/540.png",
            "score": "1"
        },
        "video_link": [
            {
                "name": "Replay",
                "url": "https://vod.starxcdn.xyz/vod/uk_premiersports1-1745341200-7800.mp4/tracks-v3a1/mono.m3u8?auth_key=1746060256-3284c03980204a62a78e0a0fb510d581-0-1c6f42d4043eef1bc3b6733bc011edd2"
            }
        ]
    },
    {
        "time": "16:05",
        "league": "Pro League",
        "home_team": {
            "name": "Damac",
            "logo": "https://media-sport.b-cdn.net/football/teams/2956.png",
            "score": "2"
        },
        "away_team": {
            "name": "Al-Nassr",
            "logo": "https://media-sport.b-cdn.net/football/teams/2939.png",
            "score": "3"
        },
        "video_link": [
            {
                "name": "Replay",
                "url": "https://vod.starxcdn.xyz/vod/us_fs2-1745337600-7800.mp4/tracks-v1a1/mono.m3u8?auth_key=1746060257-5ff898bc86ea4b31bdb72d7409d69ac6-0-356d0d1761fcb22ee7f23989f5cb2b7f"
            }
        ]
    },
    {
        "time": "19:00",
        "league": "Premier League",
        "home_team": {
            "name": "Tottenham",
            "logo": "https://media-sport.b-cdn.net/football/teams/47.png",
            "score": "1"
        },
        "away_team": {
            "name": "Nottingham Forest",
            "logo": "https://media-sport.b-cdn.net/football/teams/65.png",
            "score": "2"
        },
        "video_link": [
            {
                "name": "Replay",
                "url": "https://vod.starxcdn.xyz/vod/uk_ssepl-1745262000-7800.mp4/tracks-v3a1/mono.m3u8?auth_key=1746060258-5c5496280cbc458b8d5ebfd299a85684-0-9121072f54a3447b97e9d4266c2a7d76"
            }
        ]
    },
    {
        "time": "19:00",
        "league": "La Liga",
        "home_team": {
            "name": "Girona",
            "logo": "https://media-sport.b-cdn.net/football/teams/547.png",
            "score": "1"
        },
        "away_team": {
            "name": "Real Betis",
            "logo": "https://media-sport.b-cdn.net/football/teams/543.png",
            "score": "3"
        },
        "video_link": [
            {
                "name": "Replay",
                "url": "https://vod.starxcdn.xyz/vod/espn0-1745262000-7800.mp4/tracks-v1a1/mono.m3u8?auth_key=1746060258-e575202902974a2a82ba265385467c63-0-be2f37c000112e4faf926f036b71bcdb"
            }
        ]
    },
    {
        "time": "19:00",
        "league": "La Liga",
        "home_team": {
            "name": "Real Madrid",
            "logo": "https://media-sport.b-cdn.net/football/teams/541.png",
            "score": "1"
        },
        "away_team": {
            "name": "Athletic Club",
            "logo": "https://media-sport.b-cdn.net/football/teams/531.png",
            "score": "0"
        },
        "video_link": [
            {
                "name": "Replay",
                "url": "https://vod.starxcdn.xyz/vod/uk_premiersports1-1745175600-7800.mp4/tracks-v3a1/mono.m3u8?auth_key=1746060259-a2f23e02a7f5466ab80a5cb4f977d561-0-b547c50fbac06710406b098de3c4b73b"
            }
        ]
    },
    {
        "time": "18:45",
        "league": "Serie A",
        "home_team": {
            "name": "AC Milan",
            "logo": "https://media-sport.b-cdn.net/football/teams/489.png",
            "score": "0"
        },
        "away_team": {
            "name": "Atalanta",
            "logo": "https://media-sport.b-cdn.net/football/teams/499.png",
            "score": "1"
        },
        "video_link": [
            {
                "name": "Replay",
                "url": "https://vod.starxcdn.xyz/vod/uk_bts1-1745174700-7800.mp4/tracks-v3a1/mono.m3u8?auth_key=1746060260-d310912fba574f81ae02da2c96ca89f7-0-83fe83bc2a3fb7f660134d87d975aac8"
            }
        ]
    },
    {
        "time": "17:30",
        "league": "Bundesliga",
        "home_team": {
            "name": "FC St. Pauli",
            "logo": "https://media-sport.b-cdn.net/football/teams/186.png",
            "score": "1"
        },
        "away_team": {
            "name": "Bayer Leverkusen",
            "logo": "https://media-sport.b-cdn.net/football/teams/168.png",
            "score": "1"
        },
        "video_link": [
            {
                "name": "Replay",
                "url": "https://vod.starxcdn.xyz/vod/uk_ssfb-1745170200-7800.mp4/tracks-v1a1/mono.m3u8?auth_key=1746060261-045b272bf3094898ac85a17f7cb1fa4c-0-b80b9bc2e2db5b7f1b385ded1e9b1716"
            }
        ]
    }
]